mcp_yiqijian/__init__.py
mcp_yiqijian/server.py
mcp_yiqijian-0.6.dist-info/LICENSE
mcp_yiqijian-0.6.dist-info/METADATA
mcp_yiqijian-0.6.dist-info/WHEEL
mcp_yiqijian-0.6.dist-info/entry_points.txt
mcp_yiqijian-0.6.dist-info/top_level.txt
mcp_yiqijian-0.6.dist-info/RECORD
