Metadata-Version: 2.1
Name: mcp_yiqijian
Version: 0.6
Summary: Yiqijian mcp plugin
Author: Yiqijian
Author-email: 
License: MIT
Classifier: Intended Audience :: Developers
Classifier: License :: OSI Approved :: MIT License
Classifier: Programming Language :: Python :: 3
Classifier: Programming Language :: Python :: 3.8
Classifier: Programming Language :: Python :: 3.9
Classifier: Programming Language :: Python :: 3.10
Classifier: Programming Language :: Python :: 3.11
Classifier: Programming Language :: Python :: 3.12
License-File: LICENSE
Requires-Dist: fastmcp >=2.2.10
Requires-Dist: httpx >=0.28.1
